Metadata-Version: 2.4
Name: toolforge-jobs-cli
Version: 16.1.23
Summary: Command line interface for the Toolforge Jobs framework
Author: Arturo Borrero Gonzalez
Author-email: aborrero@wikimedia.org
License: GPL-3.0-or-later
License-File: LICENSE
Requires-Dist: PyYAML
Requires-Dist: requests
Requires-Dist: tabulate
Requires-Dist: toolforge-weld>=1.6.1
Dynamic: author
Dynamic: author-email
Dynamic: license
Dynamic: license-file
Dynamic: requires-dist
Dynamic: summary
